{"menu":
    [
        {
            "title": "colinraffel.com",
            "url": "http://colinraffel.com"
        },
        {
            "title": "CV",
            "url": "http://colinraffel.com/cv.html"
        },
        {
            "title": "Blog",
            "url": "http://colinraffel.com/blog"
        },
        {
            "title": "Wiki",
            "url": "http://colinraffel.com/wiki"
        },
        {
            "title": "Github",
            "url": "http://github.com/craffel"
        },
        {
            "title": "Google Scholar",
            "url": "https://scholar.google.com/citations?user=I66ZBYwAAAAJ&hl=en"
        },
        {
            "title": "E-mail",
            "url": "&#109;&#97;&#105;&#108;&#116;&#111;&#58;&#99;&#114;&#97;&#102;&#102;&#101;&#108;&#64;&#103;&#109;&#97;&#105;&#108;&#46;&#99;&#111;&#109;"
        }
    ]
}
